{
  "folder": "1ZMkLwIYG4BMOM6U",
  "type": "pf1-pow.maneuver",
  "name": "Fertile Flow",
  "system": {
    "htmlFields": [
      "description.value"
    ],
    "filePathFields": {
      "img": [
        "IMAGE"
      ]
    },
    "discipline": "Intoxicating Petal",
    "level": 3,
    "initTime": {
      "value": 1,
      "units": "swift"
    },
    "maneuverType": "Boost",
    "saveType": "None",
    "saveEffect": "Half",
    "ready": false,
    "granted": false,
    "stanceActive": false,
    "class": "",
    "uses": {
      "per": "charges",
      "value": 0,
      "maxFormula": "1",
      "autoDeductChargesCost": "",
      "rechargeFormula": ""
    },
    "actions": [],
    "description": {
      "value": "<p>Soil, flesh, it is all the same in the end. Make an attack. If it hits, the target is inflicted with [sprout 2] and takes an additional 1d6 damage. If it is already sprouted it instead takes an additional 3d6 points of damage, and you may tear off up to 1 stack of sprout from the target.</p>"
    },
    "changes": [],
    "contextNotes": [],
    "sources": []
  },
  "_id": "75PHCdlrJheosAmc",
  "img": "icons/magic/nature/elemental-plant-humanoid.webp",
  "effects": [],
  "sort": 0,
  "ownership": {
    "default": 0,
    "5hV992ZqcBAWMYZs": 3
  },
  "flags": {},
  "_stats": {
    "compendiumSource": null,
    "duplicateSource": null,
    "exportSource": null,
    "coreVersion": "13.351",
    "systemId": "pf1",
    "systemVersion": "11.11",
    "createdTime": 1777391424242,
    "modifiedTime": 1777396105329,
    "lastModifiedBy": "5hV992ZqcBAWMYZs"
  },
  "_key": "!items!75PHCdlrJheosAmc"
}
