{
  "type": "feat",
  "system": {
    "description": {
      "value": "<p>At 12th level, a warder can use mental and physical resiliency to avoid certain attacks. If she makes a successful Fortitude or Will saving throw against an attack that has a reduced effect on a successful save, she instead avoids the effect entirely. A helpless warder does not gain the benefit of the stalwart ability.</p>",
      "instructions": ""
    },
    "tags": [],
    "actions": [],
    "attackNotes": [],
    "effectNotes": [],
    "uses": {
      "value": null,
      "per": "",
      "autoDeductChargesCost": "",
      "maxFormula": "",
      "rechargeFormula": ""
    },
    "changes": [],
    "changeFlags": {
      "immuneToMorale": false,
      "loseDexToAC": false,
      "noMediumEncumbrance": false,
      "noHeavyEncumbrance": false,
      "mediumArmorFullSpeed": false,
      "heavyArmorFullSpeed": false,
      "lowLightVision": false,
      "seeInvisibility": false,
      "seeInDarkness": false
    },
    "contextNotes": [
      {
        "text": "Stalwart: Effects that have reduced effects on a successful fortitude save instead have no effect on a successful fortitude save",
        "target": "fort"
      },
      {
        "text": "Stalwart: Effects that have reduced effects on a successful woll save instead have no effect on a successful will save",
        "target": "will"
      }
    ],
    "links": {
      "children": [],
      "charges": []
    },
    "tag": "",
    "armorProf": [],
    "weaponProf": [],
    "languages": [],
    "flags": {
      "boolean": {},
      "dictionary": {}
    },
    "scriptCalls": [],
    "subType": "classFeat",
    "traitType": "",
    "traitCategory": "",
    "racePoints": null,
    "abilityType": "ex",
    "associations": {
      "classes": []
    },
    "showInQuickbar": false,
    "crOffset": "",
    "inherited": false,
    "acquired": false,
    "simple": false,
    "summons": false,
    "disabled": false,
    "classSkills": {
      "acr": false,
      "apr": false,
      "art": false,
      "ahp": false,
      "blf": false,
      "clm": false,
      "ckg": false,
      "crf": false,
      "dip": false,
      "dev": false,
      "dis": false,
      "esc": false,
      "fly": false,
      "han": false,
      "hea": false,
      "int": false,
      "kar": false,
      "kdu": false,
      "ken": false,
      "kge": false,
      "khi": false,
      "klo": false,
      "kmt": false,
      "kna": false,
      "kno": false,
      "kpl": false,
      "kre": false,
      "lin": false,
      "lor": false,
      "per": false,
      "prf": false,
      "pro": false,
      "rid": false,
      "sen": false,
      "slt": false,
      "spl": false,
      "ste": false,
      "sur": false,
      "swm": false,
      "umd": false
    },
    "class": "warder",
    "showInCombat": false
  },
  "name": "Stalwart",
  "img": "systems/pf1/icons/skills/blue_18.jpg",
  "effects": [],
  "folder": "sxV5xzdjvGAHduBl",
  "flags": {
    "scene-packer": {
      "hash": "7ac64c9de35aa2cbb42cab218ea89a7bd1d655ce"
    },
    "lilhelper": {
      "item": {
        "hideAttacks": false,
        "autoPowerAttack": false,
        "keen": false,
        "skipDialog": 0,
        "rollmodeOverride": "",
        "rollOverride": ""
      }
    }
  },
  "_stats": {
    "compendiumSource": null,
    "duplicateSource": null,
    "exportSource": null,
    "coreVersion": "13.347",
    "systemId": "pf1",
    "systemVersion": "11.8",
    "createdTime": 1757766494128,
    "modifiedTime": 1757766494851,
    "lastModifiedBy": "jI6iseAymTC0jkXd"
  },
  "ownership": {
    "default": 0,
    "jI6iseAymTC0jkXd": 3
  },
  "_id": "PMcvPRLKK8ewUV1Z",
  "sort": 700000,
  "_key": "!items!PMcvPRLKK8ewUV1Z"
}
